{
  "realm": "zypocare",
  "enabled": true,
  "displayName": "ZypoCare",
  "clients": [
    {
      "clientId": "zypocare-web",
      "enabled": true,
      "publicClient": true,
      "redirectUris": [
        "http://localhost:3000/*"
      ],
      "webOrigins": [
        "http://localhost:3000"
      ],
      "protocol": "openid-connect",
      "standardFlowEnabled": true,
      "directAccessGrantsEnabled": true
    },
    {
      "clientId": "zypocare-api",
      "enabled": true,
      "publicClient": false,
      "protocol": "openid-connect",
      "serviceAccountsEnabled": true,
      "standardFlowEnabled": false,
      "directAccessGrantsEnabled": false
    }
  ],
  "roles": {
    "realm": [
      {
        "name": "SUPER_ADMIN"
      },
      {
        "name": "BRANCH_ADMIN"
      },
      {
        "name": "FRONT_OFFICE"
      },
      {
        "name": "DOCTOR"
      },
      {
        "name": "NURSE"
      },
      {
        "name": "BILLING"
      },
      {
        "name": "DIAGNOSTICS"
      },
      {
        "name": "PHARMACY"
      },
      {
        "name": "OPS"
      },
      {
        "name": "SURVEILLANCE_OFFICER"
      }
    ]
  },
  "users": [
    {
      "username": "superadmin",
      "enabled": true,
      "emailVerified": true,
      "email": "superadmin@zypocare.local",
      "firstName": "Super",
      "lastName": "Admin",
      "credentials": [
        {
          "type": "password",
          "value": "admin",
          "temporary": false
        }
      ],
      "realmRoles": [
        "SUPER_ADMIN"
      ]
    }
  ]
}